[
  { "name": "sapporo", "text": "北海道" },
  { "name": "aomori", "text": "青森" },
  { "name": "morioka", "text": "岩手" },
  { "name": "sendai", "text": "宮城" },
  { "name": "akita", "text": "秋田" },
  { "name": "yamagata", "text": "山形" },
  { "name": "fukushima", "text": "福島" },
  { "name": "mito", "text": "茨城" },
  { "name": "utsunomiya", "text": "栃木" },
  { "name": "Maebashi", "text": "群馬" },
  { "name": "saitama", "text": "埼玉" },
  { "name": "chiba", "text": "千葉" },
  { "name": "shinjuku", "text": "東京" },
  { "name": "yokohama", "text": "神奈川" },
  { "name": "niigata", "text": "新潟" },
  { "name": "toyama", "text": "富山" },
  { "name": "kanazawa", "text": "金沢" },
  { "name": "Fukui", "text": "福井" },
  { "name": "kofu", "text": "山梨" },
  { "name": "nagano", "text": "長野" },
  { "name": "gifu", "text": "岐阜" },
  { "name": "shizuoka", "text": "静岡" },
  { "name": "nagoya", "text": "愛知" },
  { "name": "tsu", "text": "三重" },
  { "name": "otsu", "text": "滋賀" },
  { "name": "kyoto", "text": "京都" },
  { "name": "osaka", "text": "大阪" },
  { "name": "kobe", "text": "兵庫" },
  { "name": "nara", "text": "奈良" },
  { "name": "wakayama", "text": "和歌山" },
  { "name": "tottori", "text": "鳥取" },
  { "name": "matsue", "text": "島根" },
  { "name": "okayama", "text": "岡山" },
  { "name": "hiroshima", "text": "広島" },
  { "name": "yamaguchi", "text": "山口" },
  { "name": "tokushima", "text": "徳島" },
  { "name": "takamatsu", "text": "香川" },
  { "name": "matsuyama", "text": "愛媛" },
  { "name": "Kochi", "text": "高知" },
  { "name": "fukuoka", "text": "福岡" },
  { "name": "saga", "text": "佐賀" },
  { "name": "nagasaki", "text": "長崎" },
  { "name": "kumamoto", "text": "熊本" },
  { "name": "oita", "text": "大分" },
  { "name": "miyazaki", "text": "宮崎" },
  { "name": "kagoshima", "text": "鹿児島" },
  { "name": "naha", "text": "沖縄" }
]
